quakemigrate-1.2.1.dist-info/RECORD
quakemigrate-1.2.1.dist-info/WHEEL
quakemigrate-1.2.1.dist-info/top_level.txt
quakemigrate-1.2.1.dist-info/METADATA
quakemigrate-1.2.1.dist-info/licenses/LICENSE
quakemigrate/util.py
quakemigrate/__init__.py
quakemigrate/core/lib.py
quakemigrate/core/__init__.py
quakemigrate/core/libnames.py
quakemigrate/core/src/qmlib.def
quakemigrate/core/src/qmlib.cpython-39-darwin.so
quakemigrate/core/src/qmlib.h
quakemigrate/core/src/migratelib.c
quakemigrate/core/src/onsetlib.c
quakemigrate/plot/event.py
quakemigrate/plot/amplitudes.py
quakemigrate/plot/__init__.py
quakemigrate/plot/phase_picks.py
quakemigrate/plot/trigger.py
quakemigrate/io/event.py
quakemigrate/io/scanmseed.py
quakemigrate/io/cut_waveforms.py
quakemigrate/io/amplitudes.py
quakemigrate/io/__init__.py
quakemigrate/io/core.py
quakemigrate/io/coalescence.py
quakemigrate/io/triggered_events.py
quakemigrate/io/availability.py
quakemigrate/io/data.py
quakemigrate/lut/create_lut.py
quakemigrate/lut/__init__.py
quakemigrate/lut/lut.py
quakemigrate/.dylibs/libomp.dylib
quakemigrate/export/to_mfast.py
quakemigrate/export/__init__.py
quakemigrate/export/to_nlloc.py
quakemigrate/export/to_snuffler.py
quakemigrate/export/to_obspy.py
quakemigrate/signal/__init__.py
quakemigrate/signal/scan.py
quakemigrate/signal/trigger.py
quakemigrate/signal/local_mag/magnitude.py
quakemigrate/signal/local_mag/amplitude.py
quakemigrate/signal/local_mag/__init__.py
quakemigrate/signal/local_mag/local_mag.py
quakemigrate/signal/pickers/__init__.py
quakemigrate/signal/pickers/base.py
quakemigrate/signal/pickers/gaussian.py
quakemigrate/signal/onsets/__init__.py
quakemigrate/signal/onsets/stalta.py
quakemigrate/signal/onsets/base.py
