Metadata-Version: 2.4
Name: quakemigrate
Version: 1.2.1
Summary: A Python package for automatic earthquake detection and location using waveform migration and stacking.
Author-email: The QuakeMigrate Development Team <quakemigrate.developers@gmail.com>, Tom Winder <tom.winder@esc.cam.ac.uk>, Conor Bacon <cbacon@ldeo.columbia.edu>
Maintainer-email: Tom Winder <tom.winder@esc.cam.ac.uk>, Conor Bacon <cbacon@ldeo.columbia.edu>
License: GPLv3
Project-URL: GitHub, https://github.com/QuakeMigrate/QuakeMigrate
Project-URL: Issues, https://github.com/QuakeMigrate/QuakeMigrate/issues
Keywords: seismic event detection,seismic event location,waveform migration,array,seismic,seismology,earthquake,seismic waves,waveform,processing
Classifier: Development Status :: 5 - Production/Stable
Classifier: Intended Audience :: Science/Research
Classifier: Topic :: Scientific/Engineering
Classifier: Natural Language :: English
Classifier: License :: OSI Approved :: GNU General Public License v3 (GPLv3)
Classifier: Operating System :: OS Independent
Classifier: Programming Language :: Python
Classifier: Programming Language :: Python :: 3
Classifier: Programming Language :: Python :: 3.9
Classifier: Programming Language :: Python :: 3.10
Classifier: Programming Language :: Python :: 3.11
Classifier: Programming Language :: Python :: 3.12
Requires-Python: >=3.9
License-File: LICENSE
Requires-Dist: matplotlib
Requires-Dist: numpy
Requires-Dist: obspy>=1.3
Requires-Dist: pandas
Requires-Dist: pyproj>=2.5
Requires-Dist: scipy
Provides-Extra: dev
Requires-Dist: ipython; extra == "dev"
Requires-Dist: pre-commit; extra == "dev"
Requires-Dist: ruff; extra == "dev"
Requires-Dist: coverage; extra == "dev"
Provides-Extra: docs
Requires-Dist: docutils<0.17; extra == "docs"
Requires-Dist: Sphinx>=4.3.0; extra == "docs"
Requires-Dist: sphinx_rtd_theme>=0.5.1; extra == "docs"
Provides-Extra: fmm
Requires-Dist: scikit-fmm; extra == "fmm"
Provides-Extra: manuscript
Requires-Dist: memray; extra == "manuscript"
Requires-Dist: seaborn; extra == "manuscript"
Dynamic: license-file
